spectraclassify/__init__.py
spectraclassify/main.py
spectraclassify/prediction_service.py
spectraclassify/test.py
spectraclassify/training_service.py
spectraclassify/utility/__init__.py
spectraclassify/utility/config_manager.py
spectraclassify/utility/data_manager.py
spectraclassify/utility/keras_callbacks.py
spectraclassify/utility/model_builder.py
spectraclassify/utility/pretrained_models.py
spectraclassify/utility/utils.py
SpectraClassify-0.0.7.dist-info/LICENSE
SpectraClassify-0.0.7.dist-info/METADATA
SpectraClassify-0.0.7.dist-info/WHEEL
SpectraClassify-0.0.7.dist-info/entry_points.txt
SpectraClassify-0.0.7.dist-info/top_level.txt
SpectraClassify-0.0.7.dist-info/RECORD
