Metadata-Version: 2.1
Name: SpectraClassify
Version: 0.0.7
Summary: SpectraClassify is a python package for zero code image classification within the browser
Home-page: https://github.com/sadhiin/spectraclassify
Author: Sadhin
Author-email: sadhin.aiub.cse@gmail.com
Classifier: Development Status :: 3 - Alpha
Classifier: Intended Audience :: Developers
Classifier: Topic :: Software Development :: Build Tools
Classifier: License :: OSI Approved :: MIT License
Classifier: Programming Language :: Python :: 3
Classifier: Programming Language :: Python :: 3.10
License-File: LICENSE
Requires-Dist: globals ==0.3.36
Requires-Dist: numpy ==1.24.3
Requires-Dist: opencv-python ==4.8.1.78
Requires-Dist: tensorflow ==2.13
Requires-Dist: pillow ==10.2.0
Requires-Dist: Flask ==3.0.0
Requires-Dist: Flask-Cors ==4.0.0
Requires-Dist: python-box ==7.1.1
Requires-Dist: ensure ==1.0.4
